pypi_client/__init__.py
pypi_client/cli.py
pypi_client/github_auth.py
pypi_client/repo.py
pypi_client/service.py
pypi_client/types/__init__.py
pypi_client/types/github_repo.py
pypi_client/types/pepy_tech.py
pypi_client/types/pypi_entry.py
pypi_client/user_config.py
pypi_client-0.2.3.dist-info/entry_points.txt
pypi_client-0.2.3.dist-info/WHEEL
pypi_client-0.2.3.dist-info/METADATA
pypi_client-0.2.3.dist-info/RECORD
